rosbag_dash/__init__.py
rosbag_dash/bagdash.py
rosbag_dash/bagplot.py
rosbag_dash/bagreader.py
rosbag_dash/helper.py
rosbag_dash-0.0.0.dist-info/LICENSE
rosbag_dash-0.0.0.dist-info/METADATA
rosbag_dash-0.0.0.dist-info/WHEEL
rosbag_dash-0.0.0.dist-info/top_level.txt
rosbag_dash-0.0.0.dist-info/RECORD
