Metadata-Version: 2.1
Name: rosbag-dash
Version: 0.0.0
Summary: Provides modules to create plotly figures and dash apps from ROS bag files.
Home-page: https://github.com/aykutkabaoglu/rosbag-dash
Author: Aykut Kabaoglu
Author-email: aykutkabaoglu@gmail.com
License: MIT
Platform: UNKNOWN
License-File: LICENSE
Requires-Dist: numpy
Requires-Dist: pycryptodomex
Requires-Dist: pyyaml
Requires-Dist: rospkg
Requires-Dist: ipython
Requires-Dist: gnupg
Requires-Dist: pandas
Requires-Dist: setuptools-scm
Requires-Dist: importlib-resources
Requires-Dist: plotly
Requires-Dist: dash
Requires-Dist: scipy
